Metadata-Version: 2.1
Name: wealthsimple-trade-python
Version: 1.1.0
Summary: Python wrapper for the Wealthsimple Trade API
Home-page: https://github.com/seansullivan44/Wealthsimple-Trade-Python
Author: Sean Sullivan
Author-email: sean.mc.sullivan@gmail.com
License: MIT
Project-URL: Documentation, https://Wealthsimple-Trade-Python.readthedocs.io/
Project-URL: Changelog, https://Wealthsimple-Trade-Python.readthedocs.io/en/latest/changelog.html
Project-URL: Issue Tracker, https://github.com/seansullivan44/Wealthsimple-Trade-Python/issues
Keywords: wealthsimple,trade,finance,stocks,market,api,wrapper
Platform: UNKNOWN
Classifier: Development Status :: 5 - Production/Stable
Classifier: Intended Audience :: Developers
Classifier: License :: OSI Approved :: MIT License
Classifier: Operating System :: Unix
Classifier: Operating System :: POSIX
Classifier: Operating System :: Microsoft :: Windows
Classifier: Programming Language :: Python
Classifier: Programming Language :: Python :: 3
Classifier: Programming Language :: Python :: 3.5
Classifier: Programming Language :: Python :: 3.6
Classifier: Programming Language :: Python :: 3.7
Classifier: Programming Language :: Python :: 3.8
Classifier: Programming Language :: Python :: Implementation :: CPython
Classifier: Programming Language :: Python :: Implementation :: PyPy
Classifier: Topic :: Utilities
Requires-Python: !=3.0.*, !=3.1.*, !=3.2.*, !=3.3.*, !=3.4.*
